PDSim/__init__.py
PDSim/misc/__init__.py
PDSim/misc/error_bar.py
PDSim/misc/datatypes.cpython-37m-x86_64-linux-gnu.so
PDSim/misc/datatypes.pxd
PDSim/misc/stl_utilities.cpython-37m-x86_64-linux-gnu.so
PDSim/misc/solvers.py
PDSim/misc/scipylike.cpython-37m-x86_64-linux-gnu.so
PDSim/misc/hdf5.py
PDSim/misc/polymath_sample.py
PDSim/misc/stl_utilities.pxd
PDSim/misc/clipper/main.py
PDSim/misc/clipper/setup.py
PDSim/misc/clipper/__init__.py
PDSim/misc/clipper/pyclipper.cpython-37m-x86_64-linux-gnu.so
PDSim/plot/__init__.py
PDSim/plot/plots.py
PDSim/core/__init__.py
PDSim/core/journal_bearing.py
PDSim/core/bearings.py
PDSim/core/containers.pxd
PDSim/core/motor.py
PDSim/core/containers.cpython-37m-x86_64-linux-gnu.so
PDSim/core/_bearings.cpython-37m-x86_64-linux-gnu.so
PDSim/core/callbacks.pxd
PDSim/core/integrators.py
PDSim/core/core.py
PDSim/core/callbacks.cpython-37m-x86_64-linux-gnu.so
PDSim/core/mobility.py
PDSim/recip/__init__.py
PDSim/recip/_recip.pxd
PDSim/recip/_recip.cpython-37m-x86_64-linux-gnu.so
PDSim/recip/core.py
PDSim/scroll/common_scroll_geo.cpython-37m-x86_64-linux-gnu.so
PDSim/scroll/scroll_geo.py
PDSim/scroll/expander.py
PDSim/scroll/_scroll.pxd
PDSim/scroll/__init__.py
PDSim/scroll/symm_scroll_geo.pxd
PDSim/scroll/plots.py
PDSim/scroll/_scroll.cpython-37m-x86_64-linux-gnu.so
PDSim/scroll/symm_scroll_geo.cpython-37m-x86_64-linux-gnu.so
PDSim/scroll/core.py
PDSim/scroll/common_scroll_geo.pxd
PDSim/flow/__init__.py
PDSim/flow/flow.cpython-37m-x86_64-linux-gnu.so
PDSim/flow/flow_models.cpython-37m-x86_64-linux-gnu.so
PDSim/flow/flow_models.pxd
PDSim/flow/fanno.cpython-37m-x86_64-linux-gnu.so
PDSim/flow/flow.pxd
PDSim-2.14.dist-info/WHEEL
PDSim-2.14.dist-info/RECORD
PDSim-2.14.dist-info/METADATA
PDSim-2.14.dist-info/LICENSE
PDSim-2.14.dist-info/top_level.txt
